setup.py
UnknownVPN/__init__.py
UnknownVPN/config.py
UnknownVPN/main.py
UnknownVPN/structs.py
UnknownVPN.egg-info/PKG-INFO
UnknownVPN.egg-info/SOURCES.txt
UnknownVPN.egg-info/dependency_links.txt
UnknownVPN.egg-info/requires.txt
UnknownVPN.egg-info/top_level.txt