Metadata-Version: 2.1
Name: UnknownVPN
Version: 1.0.3
Summary: Simple Library for UnknownVPN Robot API documentation.
Home-page: UNKNOWN
Author: Confused Character
License: UNKNOWN
Platform: UNKNOWN
